odoo/addons/stock_landed_costs_delivery/README.rst
odoo/addons/stock_landed_costs_delivery/__init__.py
odoo/addons/stock_landed_costs_delivery/__manifest__.py
odoo/addons/stock_landed_costs_delivery/i18n/it.po
odoo/addons/stock_landed_costs_delivery/i18n/stock_landed_costs_delivery.pot
odoo/addons/stock_landed_costs_delivery/models/__init__.py
odoo/addons/stock_landed_costs_delivery/models/delivery_carrier.py
odoo/addons/stock_landed_costs_delivery/models/purchase_order.py
odoo/addons/stock_landed_costs_delivery/models/stock_picking.py
odoo/addons/stock_landed_costs_delivery/readme/CONTRIBUTORS.rst
odoo/addons/stock_landed_costs_delivery/readme/DESCRIPTION.rst
odoo/addons/stock_landed_costs_delivery/readme/USAGE.rst
odoo/addons/stock_landed_costs_delivery/static/description/icon.png
odoo/addons/stock_landed_costs_delivery/static/description/index.html
odoo/addons/stock_landed_costs_delivery/tests/__init__.py
odoo/addons/stock_landed_costs_delivery/tests/test_purchase_order.py
odoo/addons/stock_landed_costs_delivery/views/delivery_carrier_view.xml
odoo_addon_stock_landed_costs_delivery-16.0.1.0.0.2.dist-info/METADATA
odoo_addon_stock_landed_costs_delivery-16.0.1.0.0.2.dist-info/WHEEL
odoo_addon_stock_landed_costs_delivery-16.0.1.0.0.2.dist-info/top_level.txt
odoo_addon_stock_landed_costs_delivery-16.0.1.0.0.2.dist-info/RECORD
